beautifulworld/__init__.py
beautifulworld/city.py
beautifulworld-0.0.3.dist-info/LICENSE
beautifulworld-0.0.3.dist-info/METADATA
beautifulworld-0.0.3.dist-info/WHEEL
beautifulworld-0.0.3.dist-info/top_level.txt
beautifulworld-0.0.3.dist-info/RECORD
